[
  {
    "id": 1,
    "nombre": "Producto 1",
    "precio": 25,
    "descripcion": "Descripcion del producto 1",
    "codigo": "123456789",
    "foto": "https://www.google.com/imgres?imgurl=https%3A%2F%2Fwww.gstatic.com%2Fimages%2Fbranding%2Fproduct%2F1x%2Fgoogleg_lodp.png&imgrefurl=https%3A%",
    "stock": 20,
    "timestamp": 1659547653787
  },
  {
    "id": 2,
    "nombre": "Producto 2",
    "precio": 25,
    "descripcion": "Descripcion del producto 2",
    "codigo": "123456789",
    "foto": "https://www.google.com/imgres?imgurl=https%3A%2F%2Fwww.gstatic.com%2Fimages%2Fbranding%2Fproduct%2F1x%2Fgoogleg_lodp.png&imgrefurl=https%3A%",
    "stock": 20,
    "timestamp": 1659547653787
  },
  {
    "id": 3,
    "nombre": "Producto 3",
    "precio": 25,
    "descripcion": "Descripcion del producto 3",
    "codigo": "123456789",
    "foto": "https://www.google.com/imgres?imgurl=https%3A%2F%2Fwww.gstatic.com%2Fimages%2Fbranding%2Fproduct%2F1x%2Fgoogleg_lodp.png&imgrefurl=https%3A%",
    "stock": 20,
    "timestamp": 1659547653787
  },
  {
    "id": 4,
    "nombre": "Producto 4",
    "precio": 25,
    "descripcion": "Descripcion del producto 4",
    "codigo": "123456789",
    "foto": "https://www.google.com/imgres?imgurl=https%3A%2F%2Fwww.gstatic.com%2Fimages%2Fbranding%2Fproduct%2F1x%2Fgoogleg_lodp.png&imgrefurl=https%3A%",
    "stock": 20,
    "timestamp": 1659547653787
  },
  {
    "id": 5,
    "nombre": "Producto 5",
    "precio": 25,
    "descripcion": "Descripcion del producto 5",
    "codigo": "123456789",
    "foto": "https://www.google.com/imgres?imgurl=https%3A%2F%2Fwww.gstatic.com%2Fimages%2Fbranding%2Fproduct%2F1x%2Fgoogleg_lodp.png&imgrefurl=https%3A%",
    "stock": 20,
    "timestamp": 1659547653787
  },
  {
    "id": 6,
    "nombre": "Producto 6",
    "precio": 25,
    "descripcion": "Descripcion del producto 6",
    "codigo": "123456789",
    "foto": "https://www.google.com/imgres?imgurl=https%3A%2F%2Fwww.gstatic.com%2Fimages%2Fbranding%2Fproduct%2F1x%2Fgoogleg_lodp.png&imgrefurl=https%3A%",
    "stock": 20,
    "timestamp": 1659547653787
  },
  {
    "id": 7,
    "nombre": "Producto 7",
    "precio": 25,
    "descripcion": "Descripcion del producto 7",
    "codigo": "123456789",
    "foto": "https://www.google.com/imgres?imgurl=https%3A%2F%2Fwww.gstatic.com%2Fimages%2Fbranding%2Fproduct%2F1x%2Fgoogleg_lodp.png&imgrefurl=https%3A%",
    "stock": 20,
    "timestamp": 1659547653787
  },
  {
    "id": 8,
    "nombre": "Producto 8",
    "precio": 25,
    "descripcion": "Descripcion del producto 8",
    "codigo": "123456789",
    "foto": "https://www.google.com/imgres?imgurl=https%3A%2F%2Fwww.gstatic.com%2Fimages%2Fbranding%2Fproduct%2F1x%2Fgoogleg_lodp.png&imgrefurl=https%3A%",
    "stock": 20,
    "timestamp": 1659547653787
  }
]
